dbt/__init__.py
dbt/adapters/obmysql/__init__.py
dbt/adapters/obmysql/__version__.py
dbt/adapters/obmysql/column.py
dbt/adapters/obmysql/connections.py
dbt/adapters/obmysql/impl.py
dbt/adapters/obmysql/relation.py
dbt/include/obmysql/__init__.py
dbt/include/obmysql/dbt_project.yml
dbt/include/obmysql/profile_template.yml
dbt/include/obmysql/sample_profiles.yml
dbt/include/obmysql/macros/adapters.sql
dbt/include/obmysql/macros/catalog.sql
dbt/include/obmysql/macros/timestamp.sql
dbt/include/obmysql/macros/relations/incremental/merge.sql
dbt/include/obmysql/macros/relations/materialized_view/alter.sql
dbt/include/obmysql/macros/relations/materialized_view/create.sql
dbt/include/obmysql/macros/relations/materialized_view/drop.sql
dbt/include/obmysql/macros/relations/table/create.sql
dbt/include/obmysql/macros/relations/table/drop.sql
dbt/include/obmysql/macros/relations/view/create.sql
dbt/include/obmysql/macros/relations/view/drop.sql
dbt/include/obmysql/macros/snapshot/helpers.sql
dbt/include/obmysql/macros/snapshot/snapshot_merge.sql
dbt/include/obmysql/macros/snapshot/strategies.sql
dbt/include/obmysql/macros/test/test.sql
dbt_oceanbase-1.0.1.dist-info/LICENCE
dbt_oceanbase-1.0.1.dist-info/METADATA
dbt_oceanbase-1.0.1.dist-info/WHEEL
dbt_oceanbase-1.0.1.dist-info/top_level.txt
dbt_oceanbase-1.0.1.dist-info/RECORD
