Metadata-Version: 2.2
Name: dbt-oceanbase
Version: 1.0.1
Summary: The OceanBase adapter plugin for dbt
Home-page: https://github.com/oceanbase/dbt-oceanbase
Author: OceanBase Developer Center
Author-email: odc@oceanbase.com
Classifier: Development Status :: 5 - Production/Stable
Classifier: License :: OSI Approved :: Apache Software License
Classifier: Operating System :: Microsoft :: Windows
Classifier: Operating System :: MacOS :: MacOS X
Classifier: Operating System :: POSIX :: Linux
Classifier: Programming Language :: Python :: 3.8
Classifier: Programming Language :: Python :: 3.9
Requires-Python: >=3.8
License-File: LICENCE
Requires-Dist: dbt-core>=1.8.0b2
Requires-Dist: mysql-connector-python<8.1,>=8.0.0
Dynamic: author
Dynamic: author-email
Dynamic: classifier
Dynamic: description
Dynamic: description-content-type
Dynamic: home-page
Dynamic: requires-dist
Dynamic: requires-python
Dynamic: summary
